check_availability/cli.py
check_availability/log.py
check_availability/main.py
check_availability/services.json
check_availability-0.1.1.dist-info/entry_points.txt
check_availability-0.1.1.dist-info/WHEEL
check_availability-0.1.1.dist-info/METADATA
check_availability-0.1.1.dist-info/RECORD
