Metadata-Version: 2.1
Name: check-availability
Version: 0.1.1
Summary: 
Home-page: https://github.com/ewen-lbh/check-availability
License: MIT
Author: ewen-lbh
Author-email: ewen.lebihan7@gmail.com
Requires-Python: >=3.6,<4.0
Classifier: License :: OSI Approved :: MIT License
Classifier: Programming Language :: Python :: 3
Classifier: Programming Language :: Python :: 3.6
Classifier: Programming Language :: Python :: 3.7
Classifier: Programming Language :: Python :: 3.8
Requires-Dist: docopt (>=0.6.2,<0.7.0)
Requires-Dist: pastel (>=0.2.0,<0.3.0)
Project-URL: Repository, https://github.com/ewen-lbh/check-availability
